apcop/__init__.py
apcop/android_scan.py
apcop/cli.py
apcop/ios_scan.py
apcop/pro_pack.py
apcop/report.py
apcop/rules.py
apcop/assets/report.css
apcop/templates/report.html
apppolicy_scanner-1.0.3.dist-info/licenses/LICENSE
apppolicy_scanner-1.0.3.dist-info/METADATA
apppolicy_scanner-1.0.3.dist-info/WHEEL
apppolicy_scanner-1.0.3.dist-info/entry_points.txt
apppolicy_scanner-1.0.3.dist-info/top_level.txt
apppolicy_scanner-1.0.3.dist-info/RECORD
