Metadata-Version: 2.4
Name: apppolicy-scanner
Version: 1.0.3
Summary: Local-first scanner that maps Apple/Google policy requirements to your iOS/Android manifests.
Requires-Python: >=3.9
License-File: LICENSE
Requires-Dist: pyyaml<7,>=6
Provides-Extra: pro
Requires-Dist: pynacl<2,>=1.5; extra == "pro"
Dynamic: license-file
